xpublish_intake_provider/__init__.py
xpublish_intake_provider/_version.py
xpublish_intake_provider/dataset_provider_plugin.py
xpublish_intake_provider-0.1.1.dist-info/LICENSE.txt
xpublish_intake_provider-0.1.1.dist-info/METADATA
xpublish_intake_provider-0.1.1.dist-info/WHEEL
xpublish_intake_provider-0.1.1.dist-info/top_level.txt
xpublish_intake_provider-0.1.1.dist-info/RECORD
