Metadata-Version: 2.1
Name: xpublish-intake-provider
Version: 0.1.1
Summary: Use Intake catalogs to load datasets into Xpublish
Author-email: Alex Kerney <akerney@gmri.org>
License: Copyright 2017 AUTHOR NAME
Project-URL: homepage, https://github.com/xpublish-community/xpublish-intake-provider
Project-URL: repository, https://github.com/xpublish-community/xpublish-intake-provider
Classifier: Programming Language :: Python :: 3 :: Only
Classifier: Programming Language :: Python :: 3.9
Classifier: Programming Language :: Python :: 3.10
Classifier: Programming Language :: Python :: 3.11
Requires-Python: >=3.9
License-File: LICENSE.txt
Requires-Dist: aiohttp
Requires-Dist: intake
Requires-Dist: numpy
Requires-Dist: requests
Requires-Dist: xpublish
